global_gender_predictor/__init__.py
global_gender_predictor/global_gender_predictor.py
global_gender_predictor/data/gender_wgnd2.0.jsonl.gz
global_gender_predictor/data/gender_wgnd2.1.jsonl.gz
global_gender_predictor/data/gender_wgnd2.2.jsonl.gz
global_gender_predictor/data/gender_wgnd2.3.jsonl.gz
global_gender_predictor/data/gender_wgnd2.4.jsonl.gz
global_gender_predictor/data/gender_wgnd2.5.jsonl.gz
global_gender_predictor/data/gender_wgnd2.6.jsonl.gz
global_gender_predictor/data/gender_wgnd2.7.jsonl.gz
global_gender_predictor/data/gender_wgnd2.8.jsonl.gz
global_gender_predictor/data/gender_wgnd2.9.jsonl.gz
global_gender_predictor/data/gender_wgnd2.a.jsonl.gz
global_gender_predictor/data/gender_wgnd2.b.jsonl.gz
global_gender_predictor/data/gender_wgnd2.c.jsonl.gz
global_gender_predictor/data/gender_wgnd2.d.jsonl.gz
global_gender_predictor/data/gender_wgnd2.e.jsonl.gz
global_gender_predictor/data/gender_wgnd2.f.jsonl.gz
global_gender_predictor-0.0.5.dist-info/licenses/LICENSE
global_gender_predictor-0.0.5.dist-info/METADATA
global_gender_predictor-0.0.5.dist-info/WHEEL
global_gender_predictor-0.0.5.dist-info/top_level.txt
global_gender_predictor-0.0.5.dist-info/RECORD
