Metadata-Version: 2.4
Name: global_gender_predictor
Version: 0.0.5
Summary: Predict gender using first name using data from World Gender Name Dictionary 2.0.
Home-page: https://github.com/attract-ai/global-gender-predictor
Author: Rianne Klaver
Author-email: "attract.ai" <hello@attract.ai>
License: MIT License
Project-URL: Homepage, https://github.com/attract-ai/global-gender-predictor
Project-URL: Bug Tracker, https://github.com/attract-ai/global-gender-predictor/issues
Classifier: Programming Language :: Python :: 3
Classifier: License :: OSI Approved :: MIT License
Classifier: Operating System :: OS Independent
Requires-Python: >=3.9
License-File: LICENSE
Dynamic: author
Dynamic: home-page
Dynamic: license-file
